Metadata-Version: 2.4
Name: morai
Version: 0.3.3
Summary: A mortality viewer
Author-email: John Koestner <johnkoestner@outlook.com>
License: The MIT License (MIT)
Project-URL: homepage, https://github.com/jkoestner/morai
Project-URL: repository, https://github.com/jkoestner/morai
Requires-Python: >=3.12
License-File: LICENSE.md
Requires-Dist: arrow>=1.3.0
Requires-Dist: colorama>=0.4.6
Requires-Dist: fastexcel>=0.14.0
Requires-Dist: ipywidgets>=8.1.5
Requires-Dist: joblib>=1.5.2
Requires-Dist: jupyterlab>=4.4.3
Requires-Dist: numpy>=2.2.6
Requires-Dist: openpyxl>=3.1.5
Requires-Dist: pandas<3.0.0,>=2.3.0
Requires-Dist: plotly>=6.2.0
Requires-Dist: polars>=1.31.0
Requires-Dist: pyarrow>=20.0.0
Requires-Dist: pymort>=2.0.1
Requires-Dist: scikit-learn>=1.7.0
Requires-Dist: seaborn>=0.13.2
Requires-Dist: shap>=0.47.2
Requires-Dist: statsmodels>=0.14.4
Requires-Dist: tqdm>=4.67.1
Requires-Dist: dash>=3.1.1
Requires-Dist: dash-ag-grid>=32.3.0
Requires-Dist: dash-bootstrap-components>=2.0.3
Requires-Dist: dash-extensions>=2.0.4
Requires-Dist: gunicorn>=23.0.0
Requires-Dist: catboost>=1.2.8
Requires-Dist: pygam>=0.10.0
Provides-Extra: dev
Requires-Dist: black>=25.1.0; extra == "dev"
Requires-Dist: isort>=6.0.1; extra == "dev"
Requires-Dist: jupyterlab-code-formatter>=3.0.2; extra == "dev"
Requires-Dist: jupyter-resource-usage>=1.1.1; extra == "dev"
Requires-Dist: pytest>=8.3.5; extra == "dev"
Requires-Dist: pytest-cov>=6.0.0; extra == "dev"
Requires-Dist: ruff>=0.11.0; extra == "dev"
Requires-Dist: sphinx<7.2,>=6.0; extra == "dev"
Requires-Dist: sphinx_rtd_theme>=3.0.2; extra == "dev"
Provides-Extra: neural
Requires-Dist: torch>=2.5.1; extra == "neural"
Provides-Extra: r
Requires-Dist: rpy2==3.5.17; extra == "r"
Dynamic: license-file
